CHANGELOG.rst
LICENSE
MANIFEST.in
README.rst
setup.cfg
setup.py
ebv_luqum/__init__.py
ebv_luqum/check.py
ebv_luqum/exceptions.py
ebv_luqum/naming.py
ebv_luqum/parser.py
ebv_luqum/parsetab.py
ebv_luqum/pretty.py
ebv_luqum/tree.py
ebv_luqum/utils.py
ebv_luqum.egg-info/PKG-INFO
ebv_luqum.egg-info/SOURCES.txt
ebv_luqum.egg-info/dependency_links.txt
ebv_luqum.egg-info/requires.txt
ebv_luqum.egg-info/top_level.txt
ebv_luqum/elasticsearch/__init__.py
ebv_luqum/elasticsearch/schema.py
ebv_luqum/elasticsearch/tree.py
ebv_luqum/elasticsearch/visitor.py