Metadata-Version: 1.1
Name: ebv-luqum
Version: 0.8.0
Summary: A Lucene query parser generating ElasticSearch queries and more !
Home-page: https://github.com/yasinmeydan/luqum
Author: Jurismarches
Author-email: contact@jurismarches.com
License: UNKNOWN
Platform: UNKNOWN
Classifier: Development Status :: 4 - Beta
Classifier: License :: OSI Approved :: GNU Lesser General Public License v3 or later (LGPLv3+)
Classifier: Intended Audience :: Developers
Classifier: Programming Language :: Python
Classifier: Programming Language :: Python :: 3.4
Classifier: Programming Language :: Python :: 3.5
Classifier: Programming Language :: Python :: 3.6
